xiuxian_mixelixir/__init__.py
xiuxian_mixelixir/mix_elixir_config.py
xiuxian_mixelixir/mixelixirutil.py
xiuxian_mixelixir-0.30.dist-info/METADATA
xiuxian_mixelixir-0.30.dist-info/WHEEL
xiuxian_mixelixir-0.30.dist-info/top_level.txt
xiuxian_mixelixir-0.30.dist-info/RECORD
